{
    "id": "9193c0ab-dce0-4665-95dc-37267da73aae",
    "name": "vdun",
    "loginUrl": "https:\/\/www.crunchyroll.com\/login",
    "successUrl": "https:\/\/www.crunchyroll.com\/discover",
    "forceRedirectUrl": "https:\/\/www.crunchyroll.com\/account\/membership",
    "successValidationUrl": "https:\/\/www.crunchyroll.com\/discover",
    "scriptJson": "[{\"type\":\"click\",\"selector\":\"[name=\\\"email\\\"]\",\"xpath\":\"\\\/html\\\/body\\\/div[2]\\\/div\\\/div[2]\\\/div[2]\\\/main\\\/div\\\/form\\\/div[1]\\\/span[1]\\\/div\\\/label\\\/input\",\"time\":5295,\"url\":\"https:\\\/\\\/sso.crunchyroll.com\\\/login?return_url=%2Fauthorize%3Fclient_id%3Dnoaihdevm_6iyg0a8l0q%26redirect_uri%3Dhttps%253A%252F%252Fwww.crunchyroll.com%252Fcallback%26response_type%3Dcookie%26state%3D%252F\",\"value\":null,\"tagName\":\"input\",\"id\":\"\",\"name\":\"email\",\"className\":\"input--mOn64 email-input__field--H4fRW\",\"innerText\":\"\",\"textContent\":\"\",\"placeholder\":\"\",\"href\":\"\",\"inputType\":\"email\",\"x\":292,\"y\":224,\"clientX\":292,\"clientY\":224,\"rect\":{\"top\":203.98692321777344,\"left\":39.999996185302734,\"width\":296.4705810546875,\"height\":33.9869270324707}},{\"type\":\"click\",\"selector\":\"#onetrust-accept-btn-handler\",\"xpath\":\"\\\/\\\/*[@id=\\\"onetrust-accept-btn-handler\\\"]\",\"time\":8304,\"url\":\"https:\\\/\\\/sso.crunchyroll.com\\\/login?return_url=%2Fauthorize%3Fclient_id%3Dnoaihdevm_6iyg0a8l0q%26redirect_uri%3Dhttps%253A%252F%252Fwww.crunchyroll.com%252Fcallback%26response_type%3Dcookie%26state%3D%252F\",\"value\":null,\"tagName\":\"button\",\"id\":\"onetrust-accept-btn-handler\",\"name\":\"\",\"className\":\"\",\"innerText\":\"OK\",\"textContent\":\"OK\",\"placeholder\":\"\",\"href\":\"\",\"inputType\":\"submit\",\"x\":126,\"y\":706,\"clientX\":126,\"clientY\":706,\"rect\":{\"top\":695.2614135742188,\"left\":19.999998092651367,\"width\":336.4705810546875,\"height\":40.63725280761719}},{\"type\":\"click\",\"selector\":\"[name=\\\"email\\\"]\",\"xpath\":\"\\\/html\\\/body\\\/div[2]\\\/div\\\/div[2]\\\/div[2]\\\/main\\\/div\\\/form\\\/div[1]\\\/span[1]\\\/div\\\/label\\\/input\",\"time\":8893,\"url\":\"https:\\\/\\\/sso.crunchyroll.com\\\/login?return_url=%2Fauthorize%3Fclient_id%3Dnoaihdevm_6iyg0a8l0q%26redirect_uri%3Dhttps%253A%252F%252Fwww.crunchyroll.com%252Fcallback%26response_type%3Dcookie%26state%3D%252F\",\"value\":null,\"tagName\":\"input\",\"id\":\"\",\"name\":\"email\",\"className\":\"input--mOn64 email-input__field--H4fRW\",\"innerText\":\"\",\"textContent\":\"\",\"placeholder\":\"\",\"href\":\"\",\"inputType\":\"email\",\"x\":295,\"y\":222,\"clientX\":295,\"clientY\":222,\"rect\":{\"top\":203.98692321777344,\"left\":39.999996185302734,\"width\":296.4705810546875,\"height\":33.9869270324707}},{\"type\":\"input\",\"selector\":\"[name=\\\"email\\\"]\",\"xpath\":\"\\\/html\\\/body\\\/div[2]\\\/div\\\/div[2]\\\/div[2]\\\/main\\\/div\\\/form\\\/div[1]\\\/span[1]\\\/div\\\/label\\\/input\",\"time\":11231,\"url\":\"https:\\\/\\\/sso.crunchyroll.com\\\/login?return_url=%2Fauthorize%3Fclient_id%3Dnoaihdevm_6iyg0a8l0q%26redirect_uri%3Dhttps%253A%252F%252Fwww.crunchyroll.com%252Fcallback%26response_type%3Dcookie%26state%3D%252F\",\"value\":\"hannahigo@yahoo.com:Renee14!\",\"tagName\":\"input\",\"id\":\"\",\"name\":\"email\",\"className\":\"input--mOn64 email-input__field--H4fRW\",\"innerText\":\"\",\"textContent\":\"\",\"placeholder\":\"\",\"href\":\"\",\"inputType\":\"email\"},{\"type\":\"input\",\"selector\":\"[name=\\\"email\\\"]\",\"xpath\":\"\\\/html\\\/body\\\/div[2]\\\/div\\\/div[2]\\\/div[2]\\\/main\\\/div\\\/form\\\/div[1]\\\/span[1]\\\/div\\\/label\\\/input\",\"time\":15712,\"url\":\"https:\\\/\\\/sso.crunchyroll.com\\\/login?return_url=%2Fauthorize%3Fclient_id%3Dnoaihdevm_6iyg0a8l0q%26redirect_uri%3Dhttps%253A%252F%252Fwww.crunchyroll.com%252Fcallback%26response_type%3Dcookie%26state%3D%252F\",\"value\":\"hannahigo@yahoo.com:\",\"tagName\":\"input\",\"id\":\"\",\"name\":\"email\",\"className\":\"input--mOn64 email-input__field--H4fRW\",\"innerText\":\"\",\"textContent\":\"\",\"placeholder\":\"\",\"href\":\"\",\"inputType\":\"email\"},{\"type\":\"input\",\"selector\":\"[name=\\\"email\\\"]\",\"xpath\":\"\\\/html\\\/body\\\/div[2]\\\/div\\\/div[2]\\\/div[2]\\\/main\\\/div\\\/form\\\/div[1]\\\/span[1]\\\/div\\\/label\\\/input\",\"time\":16569,\"url\":\"https:\\\/\\\/sso.crunchyroll.com\\\/login?return_url=%2Fauthorize%3Fclient_id%3Dnoaihdevm_6iyg0a8l0q%26redirect_uri%3Dhttps%253A%252F%252Fwww.crunchyroll.com%252Fcallback%26response_type%3Dcookie%26state%3D%252F\",\"value\":\"hannahigo@yahoo.com\",\"tagName\":\"input\",\"id\":\"\",\"name\":\"email\",\"className\":\"input--mOn64 email-input__field--H4fRW\",\"innerText\":\"\",\"textContent\":\"\",\"placeholder\":\"\",\"href\":\"\",\"inputType\":\"email\"},{\"type\":\"click\",\"selector\":\"html > body > div:nth-of-type(2) > div > div:nth-of-type(2) > div:nth-of-type(2) > main > div > form > div > span:nth-of-type(2) > div:nth-of-type(2) > label\",\"xpath\":\"\\\/html\\\/body\\\/div[2]\\\/div\\\/div[2]\\\/div[2]\\\/main\\\/div\\\/form\\\/div[1]\\\/span[2]\\\/div[2]\\\/label\",\"time\":17302,\"url\":\"https:\\\/\\\/sso.crunchyroll.com\\\/login?return_url=%2Fauthorize%3Fclient_id%3Dnoaihdevm_6iyg0a8l0q%26redirect_uri%3Dhttps%253A%252F%252Fwww.crunchyroll.com%252Fcallback%26response_type%3Dcookie%26state%3D%252F\",\"value\":null,\"tagName\":\"label\",\"id\":\"\",\"name\":\"\",\"className\":\"basic-input__label--hOfP- password-input__label--xd3LG\",\"innerText\":\"Password\\nSHOW\",\"textContent\":\"PasswordShow\",\"placeholder\":\"\",\"href\":\"\",\"inputType\":\"\",\"x\":282,\"y\":287,\"clientX\":282,\"clientY\":287,\"rect\":{\"top\":279.983642578125,\"left\":39.999996185302734,\"width\":296.4705810546875,\"height\":33.9869270324707}},{\"type\":\"click\",\"selector\":\"[name=\\\"password\\\"]\",\"xpath\":\"\\\/html\\\/body\\\/div[2]\\\/div\\\/div[2]\\\/div[2]\\\/main\\\/div\\\/form\\\/div[1]\\\/span[2]\\\/div[2]\\\/label\\\/input\",\"time\":17309,\"url\":\"https:\\\/\\\/sso.crunchyroll.com\\\/login?return_url=%2Fauthorize%3Fclient_id%3Dnoaihdevm_6iyg0a8l0q%26redirect_uri%3Dhttps%253A%252F%252Fwww.crunchyroll.com%252Fcallback%26response_type%3Dcookie%26state%3D%252F\",\"value\":null,\"tagName\":\"input\",\"id\":\"\",\"name\":\"password\",\"className\":\"input--mOn64 basic-input__field--bPk55 password-input__field--Qgoe0\",\"innerText\":\"\",\"textContent\":\"\",\"placeholder\":\"\",\"href\":\"\",\"inputType\":\"password\",\"x\":282,\"y\":287,\"clientX\":282,\"clientY\":287,\"rect\":{\"top\":279.983642578125,\"left\":39.999996185302734,\"width\":236.47874450683594,\"height\":33.9869270324707}},{\"type\":\"input\",\"selector\":\"[name=\\\"password\\\"]\",\"xpath\":\"\\\/html\\\/body\\\/div[2]\\\/div\\\/div[2]\\\/div[2]\\\/main\\\/div\\\/form\\\/div[1]\\\/span[2]\\\/div[2]\\\/label\\\/input\",\"time\":18724,\"url\":\"https:\\\/\\\/sso.crunchyroll.com\\\/login?return_url=%2Fauthorize%3Fclient_id%3Dnoaihdevm_6iyg0a8l0q%26redirect_uri%3Dhttps%253A%252F%252Fwww.crunchyroll.com%252Fcallback%26response_type%3Dcookie%26state%3D%252F\",\"value\":\"Renee14!\",\"tagName\":\"input\",\"id\":\"\",\"name\":\"password\",\"className\":\"input--mOn64 basic-input__field--bPk55 password-input__field--Qgoe0\",\"innerText\":\"\",\"textContent\":\"\",\"placeholder\":\"\",\"href\":\"\",\"inputType\":\"password\"},{\"type\":\"click\",\"selector\":\"html > body > div:nth-of-type(2) > div > div:nth-of-type(2) > div:nth-of-type(2) > main > div > form > div:nth-of-type(2) > button\",\"xpath\":\"\\\/html\\\/body\\\/div[2]\\\/div\\\/div[2]\\\/div[2]\\\/main\\\/div\\\/form\\\/div[2]\\\/button\",\"time\":19654,\"url\":\"https:\\\/\\\/sso.crunchyroll.com\\\/login?return_url=%2Fauthorize%3Fclient_id%3Dnoaihdevm_6iyg0a8l0q%26redirect_uri%3Dhttps%253A%252F%252Fwww.crunchyroll.com%252Fcallback%26response_type%3Dcookie%26state%3D%252F\",\"value\":null,\"tagName\":\"button\",\"id\":\"\",\"name\":\"\",\"className\":\"button--xqVd0 button--is-type-one--3uIzT\",\"innerText\":\"LOG IN\",\"textContent\":\"Log In\",\"placeholder\":\"\",\"href\":\"\",\"inputType\":\"submit\",\"x\":269,\"y\":377,\"clientX\":269,\"clientY\":377,\"rect\":{\"top\":355.9885559082031,\"left\":39.999996185302734,\"width\":296.4705810546875,\"height\":39.999996185302734}},{\"type\":\"click\",\"selector\":\"#onetrust-accept-btn-handler\",\"xpath\":\"\\\/\\\/*[@id=\\\"onetrust-accept-btn-handler\\\"]\",\"time\":32194,\"url\":\"https:\\\/\\\/www.crunchyroll.com\\\/discover\",\"value\":null,\"tagName\":\"button\",\"id\":\"onetrust-accept-btn-handler\",\"name\":\"\",\"className\":\"\",\"innerText\":\"OK\",\"textContent\":\"OK\",\"placeholder\":\"\",\"href\":\"\",\"inputType\":\"submit\",\"x\":254,\"y\":710,\"clientX\":254,\"clientY\":710,\"rect\":{\"top\":695.2614135742188,\"left\":19.999998092651367,\"width\":336.4705810546875,\"height\":40.63725280761719}},{\"type\":\"force_coordinate_click\",\"time\":61261,\"url\":\"https:\\\/\\\/www.crunchyroll.com\\\/discover\",\"x\":289,\"y\":261,\"clientX\":289,\"clientY\":261},{\"type\":\"force_click_area\",\"selector\":\"#content > div > div > div > div:nth-of-type(3)\",\"time\":73661,\"url\":\"https:\\\/\\\/www.crunchyroll.com\\\/discover\",\"rect\":{\"top\":199.43626403808594,\"left\":19.999998092651367,\"width\":336.4705810546875,\"height\":285.9803771972656}},{\"type\":\"click\",\"selector\":\"#content > div > div > div > div:nth-of-type(3) > div > button > div > div > div > figure > picture > img\",\"xpath\":\"\\\/html\\\/body\\\/div[1]\\\/div\\\/div[1]\\\/div\\\/div[3]\\\/div[1]\\\/button\\\/div\\\/div\\\/div\\\/figure\\\/picture\\\/img\",\"time\":75159,\"url\":\"https:\\\/\\\/www.crunchyroll.com\\\/discover\",\"value\":null,\"tagName\":\"img\",\"id\":\"\",\"name\":\"\",\"className\":\"progressive-image-base__fade--Nrn20 progressive-image-base__fade--is-ready--dMxKu content-image__image--7tGlg\",\"innerText\":\"\",\"textContent\":\"\",\"placeholder\":\"\",\"href\":\"\",\"inputType\":\"\",\"x\":133,\"y\":261,\"clientX\":133,\"clientY\":261,\"rect\":{\"top\":199.43626403808594,\"left\":60.245094299316406,\"width\":95.9967269897461,\"height\":95.9967269897461}}]",
    "userAgent": "",
    "useOcrForSuccess": false,
    "successKeywords": [],
    "failureKeywords": [],
    "extractionPoints": []
}